stolpy/__init__.py
stolpy/quantum_states.py
stolpy/symbolic_wigner.py
stolpy/tensor_algebra.py
stolpy/tensor_evaluate.py
stolpy/tensor_operator.py
stolpy/tensor_space.py
stolpy/tensor_transformation.py
stolpy-0.0.1.dist-info/LICENSE
stolpy-0.0.1.dist-info/METADATA
stolpy-0.0.1.dist-info/WHEEL
stolpy-0.0.1.dist-info/top_level.txt
stolpy-0.0.1.dist-info/RECORD
