Metadata-Version: 2.1
Name: stolpy
Version: 0.0.1
Summary: stolpy - Sperical Tensor Operator Library for PYthon: A library that is capable to simplify expressions using spherical tensor operators
Author: Lukas Huth
Project-URL: Homepage, https://github.com/LukasLikesPython/spherical_tensor_operator_library
Project-URL: Bug Tracker, https://github.com/LukasLikesPython/spherical_tensor_operator_library/issues
Classifier: Programming Language :: Python :: 3
Classifier: License :: OSI Approved :: GNU General Public License v3 or later (GPLv3+)
Requires-Python: >=3.6
License-File: LICENSE
Requires-Dist: sympy (>=1.7)
